vecspace/__init__.py
vecspace/app.py
vecspace/config.py
vecspace/errors.py
vecspace/api/__init__.py
vecspace/api/fastapi.py
vecspace/api/local.py
vecspace/api/types.py
vecspace/api/models/Collection.py
vecspace/db/__init__.py
vecspace/db/clickhouse.py
vecspace/db/duckdb.py
vecspace/db/index/__init__.py
vecspace/db/index/hnswlib.py
vecspace/server/__init__.py
vecspace/server/fastapi/__init__.py
vecspace/server/fastapi/types.py
vecspace/telemetry/__init__.py
vecspace/telemetry/events.py
vecspace/telemetry/posthog.py
vecspace/test/test_api.py
vecspace/test/test_chroma.py
vecspace/utils/__init__.py
vecspace/utils/embedding_functions.py
vecspace-0.3.21.dist-info/LICENSE
vecspace-0.3.21.dist-info/WHEEL
vecspace-0.3.21.dist-info/METADATA
vecspace-0.3.21.dist-info/RECORD
