Metadata-Version: 2.1
Name: vecspace
Version: 0.3.21
Summary: VecSpace.
Author-email: Jerry zhang <jerry.zhang.bill@gmail.com>
Requires-Python: >=3.10
Classifier: Programming Language :: Python :: 3
Classifier: License :: OSI Approved :: MIT License
Classifier: Operating System :: OS Independent
Requires-Dist: pandas >= 1.3
Requires-Dist: requests >= 2.28
Requires-Dist: pydantic >= 1.9
Requires-Dist: hnswlib >= 0.7
Requires-Dist: clickhouse_connect >= 0.5.7
Requires-Dist: sentence-transformers >= 2.2.2
Requires-Dist: duckdb >= 0.7.1
Requires-Dist: fastapi >= 0.85.1
Requires-Dist: uvicorn[standard] >= 0.18.3
Requires-Dist: numpy >= 1.21.6
Requires-Dist: posthog >= 2.4.0
Project-URL: Homepage, https://github.com/peopledata/VecSpace
